{
  "schemaVersion": 1,
  "id": "june-2024-shift-2",
  "label": "June 2024 - Shift 2",
  "session": "June 2024 session",
  "examDate": "26 July 2024",
  "subject": "Life Sciences",
  "questionCount": 145,
  "source": {
    "paperUrl": "https://drive.google.com/file/d/1h-2z0dtrkap_-kv1UIcMTft5RP_l4PRi/view?usp=drive_link",
    "answerKeyUrl": "official-answer-keys/june-2024-shift-2.pdf"
  },
  "attemptLimits": {
    "A": 15,
    "B": 35,
    "C": 25
  },
  "questions": [
    {
      "number": 1,
      "questionId": "703001",
      "section": "A",
      "sourcePage": 1,
      "sourceImages": [
        "assets/questions/june-2024-shift-2/q001-1.webp",
        "assets/questions/june-2024-shift-2/q001-2.webp",
        "assets/questions/june-2024-shift-2/q001-3.webp"
      ],
      "ocrText": "",
      "correctOptions": [
        4
      ],
      "status": "scored",
      "marks": {
        "correct": 2,
        "incorrect": -0.5
      },
      "explanation": ""
    },
    {
      "number": 2,
      "questionId": "703002",
      "section": "A",
      "sourcePage": 3,
      "sourceImages": [
        "assets/questions/june-2024-shift-2/q002-1.webp"
      ],
      "ocrText": "",
      "correctOptions": [
        2
      ],
      "status": "scored",
      "marks": {
        "correct": 2,
        "incorrect": -0.5
      },
      "explanation": ""
    },
    {
      "number": 3,
      "questionId": "703003",
      "section": "A",
      "sourcePage": 3,
      "sourceImages": [
        "assets/questions/june-2024-shift-2/q003-1.webp",
        "assets/questions/june-2024-shift-2/q003-2.webp",
        "assets/questions/june-2024-shift-2/q003-3.webp",
        "assets/questions/june-2024-shift-2/q003-4.webp"
      ],
      "ocrText": "",
      "correctOptions": [
        1
      ],
      "status": "scored",
      "marks": {
        "correct": 2,
        "incorrect": -0.5
      },
      "explanation": ""
    },
    {
      "number": 4,
      "questionId": "703004",
      "section": "A",
      "sourcePage": 6,
      "sourceImages": [
        "assets/questions/june-2024-shift-2/q004-1.webp",
        "assets/questions/june-2024-shift-2/q004-2.webp",
        "assets/questions/june-2024-shift-2/q004-3.webp"
      ],
      "ocrText": "",
      "correctOptions": [
        1
      ],
      "status": "scored",
      "marks": {
        "correct": 2,
        "incorrect": -0.5
      },
      "explanation": ""
    },
    {
      "number": 5,
      "questionId": "703005",
      "section": "A",
      "sourcePage": 8,
      "sourceImages": [
        "assets/questions/june-2024-shift-2/q005-1.webp",
        "assets/questions/june-2024-shift-2/q005-2.webp"
      ],
      "ocrText": "",
      "correctOptions": [
        1
      ],
      "status": "scored",
      "marks": {
        "correct": 2,
        "incorrect": -0.5
      },
      "explanation": ""
    },
    {
      "number": 6,
      "questionId": "703006",
      "section": "A",
      "sourcePage": 9,
      "sourceImages": [
        "assets/questions/june-2024-shift-2/q006-1.webp",
        "assets/questions/june-2024-shift-2/q006-2.webp"
      ],
      "ocrText": "",
      "correctOptions": [
        3
      ],
      "status": "scored",
      "marks": {
        "correct": 2,
        "incorrect": -0.5
      },
      "explanation": ""
    },
    {
      "number": 7,
      "questionId": "703007",
      "section": "A",
      "sourcePage": 10,
      "sourceImages": [
        "assets/questions/june-2024-shift-2/q007-1.webp"
      ],
      "ocrText": "",
      "correctOptions": [
        3
      ],
      "status": "scored",
      "marks": {
        "correct": 2,
        "incorrect": -0.5
      },
      "explanation": ""
    },
    {
      "number": 8,
      "questionId": "703008",
      "section": "A",
      "sourcePage": 10,
      "sourceImages": [
        "assets/questions/june-2024-shift-2/q008-1.webp",
        "assets/questions/june-2024-shift-2/q008-2.webp",
        "assets/questions/june-2024-shift-2/q008-3.webp",
        "assets/questions/june-2024-shift-2/q008-4.webp"
      ],
      "ocrText": "",
      "correctOptions": [
        1
      ],
      "status": "scored",
      "marks": {
        "correct": 2,
        "incorrect": -0.5
      },
      "explanation": ""
    },
    {
      "number": 9,
      "questionId": "703009",
      "section": "A",
      "sourcePage": 13,
      "sourceImages": [
        "assets/questions/june-2024-shift-2/q009-1.webp",
        "assets/questions/june-2024-shift-2/q009-2.webp",
        "assets/questions/june-2024-shift-2/q009-3.webp",
        "assets/questions/june-2024-shift-2/q009-4.webp"
      ],
      "ocrText": "",
      "correctOptions": [
        4
      ],
      "status": "scored",
      "marks": {
        "correct": 2,
        "incorrect": -0.5
      },
      "explanation": ""
    },
    {
      "number": 10,
      "questionId": "703010",
      "section": "A",
      "sourcePage": 16,
      "sourceImages": [
        "assets/questions/june-2024-shift-2/q010-1.webp",
        "assets/questions/june-2024-shift-2/q010-2.webp"
      ],
      "ocrText": "",
      "correctOptions": [
        2
      ],
      "status": "scored",
      "marks": {
        "correct": 2,
        "incorrect": -0.5
      },
      "explanation": ""
    },
    {
      "number": 11,
      "questionId": "703011",
      "section": "A",
      "sourcePage": 17,
      "sourceImages": [
        "assets/questions/june-2024-shift-2/q011-1.webp",
        "assets/questions/june-2024-shift-2/q011-2.webp"
      ],
      "ocrText": "",
      "correctOptions": [
        4
      ],
      "status": "scored",
      "marks": {
        "correct": 2,
        "incorrect": -0.5
      },
      "explanation": ""
    },
    {
      "number": 12,
      "questionId": "703012",
      "section": "A",
      "sourcePage": 18,
      "sourceImages": [
        "assets/questions/june-2024-shift-2/q012-1.webp",
        "assets/questions/june-2024-shift-2/q012-2.webp"
      ],
      "ocrText": "",
      "correctOptions": [
        3
      ],
      "status": "scored",
      "marks": {
        "correct": 2,
        "incorrect": -0.5
      },
      "explanation": ""
    },
    {
      "number": 13,
      "questionId": "703013",
      "section": "A",
      "sourcePage": 19,
      "sourceImages": [
        "assets/questions/june-2024-shift-2/q013-1.webp",
        "assets/questions/june-2024-shift-2/q013-2.webp"
      ],
      "ocrText": "",
      "correctOptions": [
        2
      ],
      "status": "scored",
      "marks": {
        "correct": 2,
        "incorrect": -0.5
      },
      "explanation": ""
    },
    {
      "number": 14,
      "questionId": "703014",
      "section": "A",
      "sourcePage": 20,
      "sourceImages": [
        "assets/questions/june-2024-shift-2/q014-1.webp",
        "assets/questions/june-2024-shift-2/q014-2.webp"
      ],
      "ocrText": "",
      "correctOptions": [
        2
      ],
      "status": "scored",
      "marks": {
        "correct": 2,
        "incorrect": -0.5
      },
      "explanation": ""
    },
    {
      "number": 15,
      "questionId": "703015",
      "section": "A",
      "sourcePage": 21,
      "sourceImages": [
        "assets/questions/june-2024-shift-2/q015-1.webp",
        "assets/questions/june-2024-shift-2/q015-2.webp",
        "assets/questions/june-2024-shift-2/q015-3.webp"
      ],
      "ocrText": "",
      "correctOptions": [
        3
      ],
      "status": "scored",
      "marks": {
        "correct": 2,
        "incorrect": -0.5
      },
      "explanation": ""
    },
    {
      "number": 16,
      "questionId": "703016",
      "section": "A",
      "sourcePage": 23,
      "sourceImages": [
        "assets/questions/june-2024-shift-2/q016-1.webp",
        "assets/questions/june-2024-shift-2/q016-2.webp"
      ],
      "ocrText": "",
      "correctOptions": [
        1
      ],
      "status": "scored",
      "marks": {
        "correct": 2,
        "incorrect": -0.5
      },
      "explanation": ""
    },
    {
      "number": 17,
      "questionId": "703017",
      "section": "A",
      "sourcePage": 24,
      "sourceImages": [
        "assets/questions/june-2024-shift-2/q017-1.webp",
        "assets/questions/june-2024-shift-2/q017-2.webp"
      ],
      "ocrText": "",
      "correctOptions": [
        3
      ],
      "status": "scored",
      "marks": {
        "correct": 2,
        "incorrect": -0.5
      },
      "explanation": ""
    },
    {
      "number": 18,
      "questionId": "703018",
      "section": "A",
      "sourcePage": 25,
      "sourceImages": [
        "assets/questions/june-2024-shift-2/q018-1.webp",
        "assets/questions/june-2024-shift-2/q018-2.webp"
      ],
      "ocrText": "",
      "correctOptions": [
        1
      ],
      "status": "scored",
      "marks": {
        "correct": 2,
        "incorrect": -0.5
      },
      "explanation": ""
    },
    {
      "number": 19,
      "questionId": "703019",
      "section": "A",
      "sourcePage": 26,
      "sourceImages": [
        "assets/questions/june-2024-shift-2/q019-1.webp",
        "assets/questions/june-2024-shift-2/q019-2.webp"
      ],
      "ocrText": "",
      "correctOptions": [
        2
      ],
      "status": "scored",
      "marks": {
        "correct": 2,
        "incorrect": -0.5
      },
      "explanation": ""
    },
    {
      "number": 20,
      "questionId": "703020",
      "section": "A",
      "sourcePage": 27,
      "sourceImages": [
        "assets/questions/june-2024-shift-2/q020-1.webp",
        "assets/questions/june-2024-shift-2/q020-2.webp"
      ],
      "ocrText": "",
      "correctOptions": [
        1
      ],
      "status": "scored",
      "marks": {
        "correct": 2,
        "incorrect": -0.5
      },
      "explanation": ""
    },
    {
      "number": 21,
      "questionId": "703021",
      "section": "B",
      "sourcePage": 28,
      "sourceImages": [
        "assets/questions/june-2024-shift-2/q021-1.webp",
        "assets/questions/june-2024-shift-2/q021-2.webp"
      ],
      "ocrText": "",
      "correctOptions": [
        3
      ],
      "status": "scored",
      "marks": {
        "correct": 2,
        "incorrect": -0.5
      },
      "explanation": ""
    },
    {
      "number": 22,
      "questionId": "703022",
      "section": "B",
      "sourcePage": 29,
      "sourceImages": [
        "assets/questions/june-2024-shift-2/q022-1.webp",
        "assets/questions/june-2024-shift-2/q022-2.webp"
      ],
      "ocrText": "",
      "correctOptions": [
        4
      ],
      "status": "scored",
      "marks": {
        "correct": 2,
        "incorrect": -0.5
      },
      "explanation": ""
    },
    {
      "number": 23,
      "questionId": "703023",
      "section": "B",
      "sourcePage": 30,
      "sourceImages": [
        "assets/questions/june-2024-shift-2/q023-1.webp",
        "assets/questions/june-2024-shift-2/q023-2.webp"
      ],
      "ocrText": "",
      "correctOptions": [
        4
      ],
      "status": "scored",
      "marks": {
        "correct": 2,
        "incorrect": -0.5
      },
      "explanation": ""
    },
    {
      "number": 24,
      "questionId": "703024",
      "section": "B",
      "sourcePage": 31,
      "sourceImages": [
        "assets/questions/june-2024-shift-2/q024-1.webp",
        "assets/questions/june-2024-shift-2/q024-2.webp"
      ],
      "ocrText": "",
      "correctOptions": [
        3
      ],
      "status": "scored",
      "marks": {
        "correct": 2,
        "incorrect": -0.5
      },
      "explanation": ""
    },
    {
      "number": 25,
      "questionId": "703025",
      "section": "B",
      "sourcePage": 32,
      "sourceImages": [
        "assets/questions/june-2024-shift-2/q025-1.webp",
        "assets/questions/june-2024-shift-2/q025-2.webp"
      ],
      "ocrText": "",
      "correctOptions": [
        4
      ],
      "status": "scored",
      "marks": {
        "correct": 2,
        "incorrect": -0.5
      },
      "explanation": ""
    },
    {
      "number": 26,
      "questionId": "703026",
      "section": "B",
      "sourcePage": 33,
      "sourceImages": [
        "assets/questions/june-2024-shift-2/q026-1.webp",
        "assets/questions/june-2024-shift-2/q026-2.webp"
      ],
      "ocrText": "",
      "correctOptions": [
        3
      ],
      "status": "scored",
      "marks": {
        "correct": 2,
        "incorrect": -0.5
      },
      "explanation": ""
    },
    {
      "number": 27,
      "questionId": "703027",
      "section": "B",
      "sourcePage": 34,
      "sourceImages": [
        "assets/questions/june-2024-shift-2/q027-1.webp",
        "assets/questions/june-2024-shift-2/q027-2.webp"
      ],
      "ocrText": "",
      "correctOptions": [
        3
      ],
      "status": "scored",
      "marks": {
        "correct": 2,
        "incorrect": -0.5
      },
      "explanation": ""
    },
    {
      "number": 28,
      "questionId": "703028",
      "section": "B",
      "sourcePage": 35,
      "sourceImages": [
        "assets/questions/june-2024-shift-2/q028-1.webp",
        "assets/questions/june-2024-shift-2/q028-2.webp"
      ],
      "ocrText": "",
      "correctOptions": [
        3
      ],
      "status": "scored",
      "marks": {
        "correct": 2,
        "incorrect": -0.5
      },
      "explanation": ""
    },
    {
      "number": 29,
      "questionId": "703029",
      "section": "B",
      "sourcePage": 36,
      "sourceImages": [
        "assets/questions/june-2024-shift-2/q029-1.webp",
        "assets/questions/june-2024-shift-2/q029-2.webp"
      ],
      "ocrText": "",
      "correctOptions": [
        3
      ],
      "status": "scored",
      "marks": {
        "correct": 2,
        "incorrect": -0.5
      },
      "explanation": ""
    },
    {
      "number": 30,
      "questionId": "703030",
      "section": "B",
      "sourcePage": 37,
      "sourceImages": [
        "assets/questions/june-2024-shift-2/q030-1.webp",
        "assets/questions/june-2024-shift-2/q030-2.webp"
      ],
      "ocrText": "",
      "correctOptions": [
        1
      ],
      "status": "scored",
      "marks": {
        "correct": 2,
        "incorrect": -0.5
      },
      "explanation": ""
    },
    {
      "number": 31,
      "questionId": "703031",
      "section": "B",
      "sourcePage": 38,
      "sourceImages": [
        "assets/questions/june-2024-shift-2/q031-1.webp",
        "assets/questions/june-2024-shift-2/q031-2.webp"
      ],
      "ocrText": "",
      "correctOptions": [
        2
      ],
      "status": "scored",
      "marks": {
        "correct": 2,
        "incorrect": -0.5
      },
      "explanation": ""
    },
    {
      "number": 32,
      "questionId": "703032",
      "section": "B",
      "sourcePage": 39,
      "sourceImages": [
        "assets/questions/june-2024-shift-2/q032-1.webp",
        "assets/questions/june-2024-shift-2/q032-2.webp",
        "assets/questions/june-2024-shift-2/q032-3.webp"
      ],
      "ocrText": "",
      "correctOptions": [
        3
      ],
      "status": "scored",
      "marks": {
        "correct": 2,
        "incorrect": -0.5
      },
      "explanation": ""
    },
    {
      "number": 33,
      "questionId": "703033",
      "section": "B",
      "sourcePage": 41,
      "sourceImages": [
        "assets/questions/june-2024-shift-2/q033-1.webp"
      ],
      "ocrText": "",
      "correctOptions": [
        3
      ],
      "status": "scored",
      "marks": {
        "correct": 2,
        "incorrect": -0.5
      },
      "explanation": ""
    },
    {
      "number": 34,
      "questionId": "703034",
      "section": "B",
      "sourcePage": 41,
      "sourceImages": [
        "assets/questions/june-2024-shift-2/q034-1.webp",
        "assets/questions/june-2024-shift-2/q034-2.webp",
        "assets/questions/june-2024-shift-2/q034-3.webp"
      ],
      "ocrText": "",
      "correctOptions": [
        1
      ],
      "status": "scored",
      "marks": {
        "correct": 2,
        "incorrect": -0.5
      },
      "explanation": ""
    },
    {
      "number": 35,
      "questionId": "703035",
      "section": "B",
      "sourcePage": 43,
      "sourceImages": [
        "assets/questions/june-2024-shift-2/q035-1.webp"
      ],
      "ocrText": "",
      "correctOptions": [
        4
      ],
      "status": "scored",
      "marks": {
        "correct": 2,
        "incorrect": -0.5
      },
      "explanation": ""
    },
    {
      "number": 36,
      "questionId": "703036",
      "section": "B",
      "sourcePage": 43,
      "sourceImages": [
        "assets/questions/june-2024-shift-2/q036-1.webp",
        "assets/questions/june-2024-shift-2/q036-2.webp"
      ],
      "ocrText": "",
      "correctOptions": [
        3
      ],
      "status": "scored",
      "marks": {
        "correct": 2,
        "incorrect": -0.5
      },
      "explanation": ""
    },
    {
      "number": 37,
      "questionId": "703037",
      "section": "B",
      "sourcePage": 44,
      "sourceImages": [
        "assets/questions/june-2024-shift-2/q037-1.webp",
        "assets/questions/june-2024-shift-2/q037-2.webp",
        "assets/questions/june-2024-shift-2/q037-3.webp"
      ],
      "ocrText": "",
      "correctOptions": [
        1
      ],
      "status": "scored",
      "marks": {
        "correct": 2,
        "incorrect": -0.5
      },
      "explanation": ""
    },
    {
      "number": 38,
      "questionId": "703038",
      "section": "B",
      "sourcePage": 46,
      "sourceImages": [
        "assets/questions/june-2024-shift-2/q038-1.webp"
      ],
      "ocrText": "",
      "correctOptions": [
        4
      ],
      "status": "scored",
      "marks": {
        "correct": 2,
        "incorrect": -0.5
      },
      "explanation": ""
    },
    {
      "number": 39,
      "questionId": "703039",
      "section": "B",
      "sourcePage": 46,
      "sourceImages": [
        "assets/questions/june-2024-shift-2/q039-1.webp",
        "assets/questions/june-2024-shift-2/q039-2.webp"
      ],
      "ocrText": "",
      "correctOptions": [
        1
      ],
      "status": "scored",
      "marks": {
        "correct": 2,
        "incorrect": -0.5
      },
      "explanation": ""
    },
    {
      "number": 40,
      "questionId": "703040",
      "section": "B",
      "sourcePage": 47,
      "sourceImages": [
        "assets/questions/june-2024-shift-2/q040-1.webp",
        "assets/questions/june-2024-shift-2/q040-2.webp"
      ],
      "ocrText": "",
      "correctOptions": [
        2
      ],
      "status": "scored",
      "marks": {
        "correct": 2,
        "incorrect": -0.5
      },
      "explanation": ""
    },
    {
      "number": 41,
      "questionId": "703041",
      "section": "B",
      "sourcePage": 48,
      "sourceImages": [
        "assets/questions/june-2024-shift-2/q041-1.webp",
        "assets/questions/june-2024-shift-2/q041-2.webp"
      ],
      "ocrText": "",
      "correctOptions": [
        2
      ],
      "status": "scored",
      "marks": {
        "correct": 2,
        "incorrect": -0.5
      },
      "explanation": ""
    },
    {
      "number": 42,
      "questionId": "703042",
      "section": "B",
      "sourcePage": 49,
      "sourceImages": [
        "assets/questions/june-2024-shift-2/q042-1.webp",
        "assets/questions/june-2024-shift-2/q042-2.webp"
      ],
      "ocrText": "",
      "correctOptions": [
        4
      ],
      "status": "scored",
      "marks": {
        "correct": 2,
        "incorrect": -0.5
      },
      "explanation": ""
    },
    {
      "number": 43,
      "questionId": "703043",
      "section": "B",
      "sourcePage": 50,
      "sourceImages": [
        "assets/questions/june-2024-shift-2/q043-1.webp",
        "assets/questions/june-2024-shift-2/q043-2.webp"
      ],
      "ocrText": "",
      "correctOptions": [
        2
      ],
      "status": "scored",
      "marks": {
        "correct": 2,
        "incorrect": -0.5
      },
      "explanation": ""
    },
    {
      "number": 44,
      "questionId": "703044",
      "section": "B",
      "sourcePage": 51,
      "sourceImages": [
        "assets/questions/june-2024-shift-2/q044-1.webp",
        "assets/questions/june-2024-shift-2/q044-2.webp"
      ],
      "ocrText": "",
      "correctOptions": [
        3
      ],
      "status": "scored",
      "marks": {
        "correct": 2,
        "incorrect": -0.5
      },
      "explanation": ""
    },
    {
      "number": 45,
      "questionId": "703045",
      "section": "B",
      "sourcePage": 52,
      "sourceImages": [
        "assets/questions/june-2024-shift-2/q045-1.webp",
        "assets/questions/june-2024-shift-2/q045-2.webp"
      ],
      "ocrText": "",
      "correctOptions": [
        2
      ],
      "status": "scored",
      "marks": {
        "correct": 2,
        "incorrect": -0.5
      },
      "explanation": ""
    },
    {
      "number": 46,
      "questionId": "703046",
      "section": "B",
      "sourcePage": 53,
      "sourceImages": [
        "assets/questions/june-2024-shift-2/q046-1.webp",
        "assets/questions/june-2024-shift-2/q046-2.webp"
      ],
      "ocrText": "",
      "correctOptions": [
        4
      ],
      "status": "scored",
      "marks": {
        "correct": 2,
        "incorrect": -0.5
      },
      "explanation": ""
    },
    {
      "number": 47,
      "questionId": "703047",
      "section": "B",
      "sourcePage": 54,
      "sourceImages": [
        "assets/questions/june-2024-shift-2/q047-1.webp",
        "assets/questions/june-2024-shift-2/q047-2.webp"
      ],
      "ocrText": "",
      "correctOptions": [
        3
      ],
      "status": "scored",
      "marks": {
        "correct": 2,
        "incorrect": -0.5
      },
      "explanation": ""
    },
    {
      "number": 48,
      "questionId": "703048",
      "section": "B",
      "sourcePage": 55,
      "sourceImages": [
        "assets/questions/june-2024-shift-2/q048-1.webp",
        "assets/questions/june-2024-shift-2/q048-2.webp"
      ],
      "ocrText": "",
      "correctOptions": [
        2
      ],
      "status": "scored",
      "marks": {
        "correct": 2,
        "incorrect": -0.5
      },
      "explanation": ""
    },
    {
      "number": 49,
      "questionId": "703049",
      "section": "B",
      "sourcePage": 56,
      "sourceImages": [
        "assets/questions/june-2024-shift-2/q049-1.webp",
        "assets/questions/june-2024-shift-2/q049-2.webp",
        "assets/questions/june-2024-shift-2/q049-3.webp"
      ],
      "ocrText": "",
      "correctOptions": [
        2
      ],
      "status": "scored",
      "marks": {
        "correct": 2,
        "incorrect": -0.5
      },
      "explanation": ""
    },
    {
      "number": 50,
      "questionId": "703050",
      "section": "B",
      "sourcePage": 58,
      "sourceImages": [
        "assets/questions/june-2024-shift-2/q050-1.webp",
        "assets/questions/june-2024-shift-2/q050-2.webp",
        "assets/questions/june-2024-shift-2/q050-3.webp",
        "assets/questions/june-2024-shift-2/q050-4.webp"
      ],
      "ocrText": "",
      "correctOptions": [
        2
      ],
      "status": "scored",
      "marks": {
        "correct": 2,
        "incorrect": -0.5
      },
      "explanation": ""
    },
    {
      "number": 51,
      "questionId": "703051",
      "section": "B",
      "sourcePage": 61,
      "sourceImages": [
        "assets/questions/june-2024-shift-2/q051-1.webp"
      ],
      "ocrText": "",
      "correctOptions": [
        3
      ],
      "status": "scored",
      "marks": {
        "correct": 2,
        "incorrect": -0.5
      },
      "explanation": ""
    },
    {
      "number": 52,
      "questionId": "703052",
      "section": "B",
      "sourcePage": 61,
      "sourceImages": [
        "assets/questions/june-2024-shift-2/q052-1.webp",
        "assets/questions/june-2024-shift-2/q052-2.webp",
        "assets/questions/june-2024-shift-2/q052-3.webp"
      ],
      "ocrText": "",
      "correctOptions": [
        1
      ],
      "status": "scored",
      "marks": {
        "correct": 2,
        "incorrect": -0.5
      },
      "explanation": ""
    },
    {
      "number": 53,
      "questionId": "703053",
      "section": "B",
      "sourcePage": 63,
      "sourceImages": [
        "assets/questions/june-2024-shift-2/q053-1.webp",
        "assets/questions/june-2024-shift-2/q053-2.webp"
      ],
      "ocrText": "",
      "correctOptions": [
        2
      ],
      "status": "scored",
      "marks": {
        "correct": 2,
        "incorrect": -0.5
      },
      "explanation": ""
    },
    {
      "number": 54,
      "questionId": "703054",
      "section": "B",
      "sourcePage": 64,
      "sourceImages": [
        "assets/questions/june-2024-shift-2/q054-1.webp"
      ],
      "ocrText": "",
      "correctOptions": [
        1
      ],
      "status": "scored",
      "marks": {
        "correct": 2,
        "incorrect": -0.5
      },
      "explanation": ""
    },
    {
      "number": 55,
      "questionId": "703055",
      "section": "B",
      "sourcePage": 64,
      "sourceImages": [
        "assets/questions/june-2024-shift-2/q055-1.webp",
        "assets/questions/june-2024-shift-2/q055-2.webp"
      ],
      "ocrText": "",
      "correctOptions": [
        1
      ],
      "status": "scored",
      "marks": {
        "correct": 2,
        "incorrect": -0.5
      },
      "explanation": ""
    },
    {
      "number": 56,
      "questionId": "703056",
      "section": "B",
      "sourcePage": 65,
      "sourceImages": [
        "assets/questions/june-2024-shift-2/q056-1.webp",
        "assets/questions/june-2024-shift-2/q056-2.webp"
      ],
      "ocrText": "",
      "correctOptions": [
        2
      ],
      "status": "scored",
      "marks": {
        "correct": 2,
        "incorrect": -0.5
      },
      "explanation": ""
    },
    {
      "number": 57,
      "questionId": "703057",
      "section": "B",
      "sourcePage": 66,
      "sourceImages": [
        "assets/questions/june-2024-shift-2/q057-1.webp",
        "assets/questions/june-2024-shift-2/q057-2.webp"
      ],
      "ocrText": "",
      "correctOptions": [
        2
      ],
      "status": "scored",
      "marks": {
        "correct": 2,
        "incorrect": -0.5
      },
      "explanation": ""
    },
    {
      "number": 58,
      "questionId": "703058",
      "section": "B",
      "sourcePage": 67,
      "sourceImages": [
        "assets/questions/june-2024-shift-2/q058-1.webp",
        "assets/questions/june-2024-shift-2/q058-2.webp",
        "assets/questions/june-2024-shift-2/q058-3.webp"
      ],
      "ocrText": "",
      "correctOptions": [
        1
      ],
      "status": "scored",
      "marks": {
        "correct": 2,
        "incorrect": -0.5
      },
      "explanation": ""
    },
    {
      "number": 59,
      "questionId": "703059",
      "section": "B",
      "sourcePage": 69,
      "sourceImages": [
        "assets/questions/june-2024-shift-2/q059-1.webp",
        "assets/questions/june-2024-shift-2/q059-2.webp"
      ],
      "ocrText": "",
      "correctOptions": [
        1
      ],
      "status": "scored",
      "marks": {
        "correct": 2,
        "incorrect": -0.5
      },
      "explanation": ""
    },
    {
      "number": 60,
      "questionId": "703060",
      "section": "B",
      "sourcePage": 70,
      "sourceImages": [
        "assets/questions/june-2024-shift-2/q060-1.webp",
        "assets/questions/june-2024-shift-2/q060-2.webp"
      ],
      "ocrText": "",
      "correctOptions": [
        1
      ],
      "status": "scored",
      "marks": {
        "correct": 2,
        "incorrect": -0.5
      },
      "explanation": ""
    },
    {
      "number": 61,
      "questionId": "703061",
      "section": "B",
      "sourcePage": 71,
      "sourceImages": [
        "assets/questions/june-2024-shift-2/q061-1.webp"
      ],
      "ocrText": "",
      "correctOptions": [
        4
      ],
      "status": "scored",
      "marks": {
        "correct": 2,
        "incorrect": -0.5
      },
      "explanation": ""
    },
    {
      "number": 62,
      "questionId": "703062",
      "section": "B",
      "sourcePage": 71,
      "sourceImages": [
        "assets/questions/june-2024-shift-2/q062-1.webp",
        "assets/questions/june-2024-shift-2/q062-2.webp",
        "assets/questions/june-2024-shift-2/q062-3.webp"
      ],
      "ocrText": "",
      "correctOptions": [
        2
      ],
      "status": "scored",
      "marks": {
        "correct": 2,
        "incorrect": -0.5
      },
      "explanation": ""
    },
    {
      "number": 63,
      "questionId": "703063",
      "section": "B",
      "sourcePage": 73,
      "sourceImages": [
        "assets/questions/june-2024-shift-2/q063-1.webp",
        "assets/questions/june-2024-shift-2/q063-2.webp"
      ],
      "ocrText": "",
      "correctOptions": [
        4
      ],
      "status": "scored",
      "marks": {
        "correct": 2,
        "incorrect": -0.5
      },
      "explanation": ""
    },
    {
      "number": 64,
      "questionId": "703064",
      "section": "B",
      "sourcePage": 74,
      "sourceImages": [
        "assets/questions/june-2024-shift-2/q064-1.webp",
        "assets/questions/june-2024-shift-2/q064-2.webp"
      ],
      "ocrText": "",
      "correctOptions": [
        3
      ],
      "status": "scored",
      "marks": {
        "correct": 2,
        "incorrect": -0.5
      },
      "explanation": ""
    },
    {
      "number": 65,
      "questionId": "703065",
      "section": "B",
      "sourcePage": 75,
      "sourceImages": [
        "assets/questions/june-2024-shift-2/q065-1.webp"
      ],
      "ocrText": "",
      "correctOptions": [
        3
      ],
      "status": "scored",
      "marks": {
        "correct": 2,
        "incorrect": -0.5
      },
      "explanation": ""
    },
    {
      "number": 66,
      "questionId": "703066",
      "section": "B",
      "sourcePage": 75,
      "sourceImages": [
        "assets/questions/june-2024-shift-2/q066-1.webp",
        "assets/questions/june-2024-shift-2/q066-2.webp",
        "assets/questions/june-2024-shift-2/q066-3.webp",
        "assets/questions/june-2024-shift-2/q066-4.webp"
      ],
      "ocrText": "",
      "correctOptions": [
        4
      ],
      "status": "scored",
      "marks": {
        "correct": 2,
        "incorrect": -0.5
      },
      "explanation": ""
    },
    {
      "number": 67,
      "questionId": "703067",
      "section": "B",
      "sourcePage": 78,
      "sourceImages": [
        "assets/questions/june-2024-shift-2/q067-1.webp",
        "assets/questions/june-2024-shift-2/q067-2.webp"
      ],
      "ocrText": "",
      "correctOptions": [
        1
      ],
      "status": "scored",
      "marks": {
        "correct": 2,
        "incorrect": -0.5
      },
      "explanation": ""
    },
    {
      "number": 68,
      "questionId": "703068",
      "section": "B",
      "sourcePage": 79,
      "sourceImages": [
        "assets/questions/june-2024-shift-2/q068-1.webp"
      ],
      "ocrText": "",
      "correctOptions": [
        3
      ],
      "status": "scored",
      "marks": {
        "correct": 2,
        "incorrect": -0.5
      },
      "explanation": ""
    },
    {
      "number": 69,
      "questionId": "703069",
      "section": "B",
      "sourcePage": 79,
      "sourceImages": [
        "assets/questions/june-2024-shift-2/q069-1.webp",
        "assets/questions/june-2024-shift-2/q069-2.webp",
        "assets/questions/june-2024-shift-2/q069-3.webp"
      ],
      "ocrText": "",
      "correctOptions": [
        3
      ],
      "status": "scored",
      "marks": {
        "correct": 2,
        "incorrect": -0.5
      },
      "explanation": ""
    },
    {
      "number": 70,
      "questionId": "703070",
      "section": "B",
      "sourcePage": 81,
      "sourceImages": [
        "assets/questions/june-2024-shift-2/q070-1.webp",
        "assets/questions/june-2024-shift-2/q070-2.webp"
      ],
      "ocrText": "",
      "correctOptions": [
        2
      ],
      "status": "scored",
      "marks": {
        "correct": 2,
        "incorrect": -0.5
      },
      "explanation": ""
    },
    {
      "number": 71,
      "questionId": "703071",
      "section": "C",
      "sourcePage": 82,
      "sourceImages": [
        "assets/questions/june-2024-shift-2/q071-1.webp"
      ],
      "ocrText": "",
      "correctOptions": [
        2
      ],
      "status": "scored",
      "marks": {
        "correct": 4,
        "incorrect": -1
      },
      "explanation": ""
    },
    {
      "number": 72,
      "questionId": "703072",
      "section": "C",
      "sourcePage": 82,
      "sourceImages": [
        "assets/questions/june-2024-shift-2/q072-1.webp",
        "assets/questions/june-2024-shift-2/q072-2.webp"
      ],
      "ocrText": "",
      "correctOptions": [
        2
      ],
      "status": "scored",
      "marks": {
        "correct": 4,
        "incorrect": -1
      },
      "explanation": ""
    },
    {
      "number": 73,
      "questionId": "703073",
      "section": "C",
      "sourcePage": 83,
      "sourceImages": [
        "assets/questions/june-2024-shift-2/q073-1.webp",
        "assets/questions/june-2024-shift-2/q073-2.webp"
      ],
      "ocrText": "",
      "correctOptions": [
        2
      ],
      "status": "scored",
      "marks": {
        "correct": 4,
        "incorrect": -1
      },
      "explanation": ""
    },
    {
      "number": 74,
      "questionId": "703074",
      "section": "C",
      "sourcePage": 84,
      "sourceImages": [
        "assets/questions/june-2024-shift-2/q074-1.webp",
        "assets/questions/june-2024-shift-2/q074-2.webp",
        "assets/questions/june-2024-shift-2/q074-3.webp"
      ],
      "ocrText": "",
      "correctOptions": [
        4
      ],
      "status": "scored",
      "marks": {
        "correct": 4,
        "incorrect": -1
      },
      "explanation": ""
    },
    {
      "number": 75,
      "questionId": "703075",
      "section": "C",
      "sourcePage": 86,
      "sourceImages": [
        "assets/questions/june-2024-shift-2/q075-1.webp",
        "assets/questions/june-2024-shift-2/q075-2.webp"
      ],
      "ocrText": "",
      "correctOptions": [
        1
      ],
      "status": "scored",
      "marks": {
        "correct": 4,
        "incorrect": -1
      },
      "explanation": ""
    },
    {
      "number": 76,
      "questionId": "703076",
      "section": "C",
      "sourcePage": 87,
      "sourceImages": [
        "assets/questions/june-2024-shift-2/q076-1.webp",
        "assets/questions/june-2024-shift-2/q076-2.webp",
        "assets/questions/june-2024-shift-2/q076-3.webp",
        "assets/questions/june-2024-shift-2/q076-4.webp"
      ],
      "ocrText": "",
      "correctOptions": [
        2
      ],
      "status": "scored",
      "marks": {
        "correct": 4,
        "incorrect": -1
      },
      "explanation": ""
    },
    {
      "number": 77,
      "questionId": "703077",
      "section": "C",
      "sourcePage": 90,
      "sourceImages": [
        "assets/questions/june-2024-shift-2/q077-1.webp",
        "assets/questions/june-2024-shift-2/q077-2.webp",
        "assets/questions/june-2024-shift-2/q077-3.webp"
      ],
      "ocrText": "",
      "correctOptions": [
        1
      ],
      "status": "scored",
      "marks": {
        "correct": 4,
        "incorrect": -1
      },
      "explanation": ""
    },
    {
      "number": 78,
      "questionId": "703078",
      "section": "C",
      "sourcePage": 92,
      "sourceImages": [
        "assets/questions/june-2024-shift-2/q078-1.webp",
        "assets/questions/june-2024-shift-2/q078-2.webp"
      ],
      "ocrText": "",
      "correctOptions": [
        1
      ],
      "status": "scored",
      "marks": {
        "correct": 4,
        "incorrect": -1
      },
      "explanation": ""
    },
    {
      "number": 79,
      "questionId": "703079",
      "section": "C",
      "sourcePage": 93,
      "sourceImages": [
        "assets/questions/june-2024-shift-2/q079-1.webp",
        "assets/questions/june-2024-shift-2/q079-2.webp",
        "assets/questions/june-2024-shift-2/q079-3.webp",
        "assets/questions/june-2024-shift-2/q079-4.webp"
      ],
      "ocrText": "",
      "correctOptions": [
        3
      ],
      "status": "scored",
      "marks": {
        "correct": 4,
        "incorrect": -1
      },
      "explanation": ""
    },
    {
      "number": 80,
      "questionId": "703080",
      "section": "C",
      "sourcePage": 96,
      "sourceImages": [
        "assets/questions/june-2024-shift-2/q080-1.webp",
        "assets/questions/june-2024-shift-2/q080-2.webp"
      ],
      "ocrText": "",
      "correctOptions": [
        4
      ],
      "status": "scored",
      "marks": {
        "correct": 4,
        "incorrect": -1
      },
      "explanation": ""
    },
    {
      "number": 81,
      "questionId": "703081",
      "section": "C",
      "sourcePage": 97,
      "sourceImages": [
        "assets/questions/june-2024-shift-2/q081-1.webp",
        "assets/questions/june-2024-shift-2/q081-2.webp",
        "assets/questions/june-2024-shift-2/q081-3.webp",
        "assets/questions/june-2024-shift-2/q081-4.webp"
      ],
      "ocrText": "",
      "correctOptions": [
        2
      ],
      "status": "scored",
      "marks": {
        "correct": 4,
        "incorrect": -1
      },
      "explanation": ""
    },
    {
      "number": 82,
      "questionId": "703082",
      "section": "C",
      "sourcePage": 100,
      "sourceImages": [
        "assets/questions/june-2024-shift-2/q082-1.webp",
        "assets/questions/june-2024-shift-2/q082-2.webp"
      ],
      "ocrText": "",
      "correctOptions": [
        1
      ],
      "status": "scored",
      "marks": {
        "correct": 4,
        "incorrect": -1
      },
      "explanation": ""
    },
    {
      "number": 83,
      "questionId": "703083",
      "section": "C",
      "sourcePage": 101,
      "sourceImages": [
        "assets/questions/june-2024-shift-2/q083-1.webp",
        "assets/questions/june-2024-shift-2/q083-2.webp",
        "assets/questions/june-2024-shift-2/q083-3.webp"
      ],
      "ocrText": "",
      "correctOptions": [
        1
      ],
      "status": "scored",
      "marks": {
        "correct": 4,
        "incorrect": -1
      },
      "explanation": ""
    },
    {
      "number": 84,
      "questionId": "703084",
      "section": "C",
      "sourcePage": 103,
      "sourceImages": [
        "assets/questions/june-2024-shift-2/q084-1.webp",
        "assets/questions/june-2024-shift-2/q084-2.webp",
        "assets/questions/june-2024-shift-2/q084-3.webp",
        "assets/questions/june-2024-shift-2/q084-4.webp"
      ],
      "ocrText": "",
      "correctOptions": [
        3
      ],
      "status": "scored",
      "marks": {
        "correct": 4,
        "incorrect": -1
      },
      "explanation": ""
    },
    {
      "number": 85,
      "questionId": "703085",
      "section": "C",
      "sourcePage": 106,
      "sourceImages": [
        "assets/questions/june-2024-shift-2/q085-1.webp",
        "assets/questions/june-2024-shift-2/q085-2.webp",
        "assets/questions/june-2024-shift-2/q085-3.webp"
      ],
      "ocrText": "",
      "correctOptions": [
        4
      ],
      "status": "scored",
      "marks": {
        "correct": 4,
        "incorrect": -1
      },
      "explanation": ""
    },
    {
      "number": 86,
      "questionId": "703086",
      "section": "C",
      "sourcePage": 108,
      "sourceImages": [
        "assets/questions/june-2024-shift-2/q086-1.webp",
        "assets/questions/june-2024-shift-2/q086-2.webp"
      ],
      "ocrText": "",
      "correctOptions": [
        4
      ],
      "status": "scored",
      "marks": {
        "correct": 4,
        "incorrect": -1
      },
      "explanation": ""
    },
    {
      "number": 87,
      "questionId": "703087",
      "section": "C",
      "sourcePage": 109,
      "sourceImages": [
        "assets/questions/june-2024-shift-2/q087-1.webp",
        "assets/questions/june-2024-shift-2/q087-2.webp",
        "assets/questions/june-2024-shift-2/q087-3.webp",
        "assets/questions/june-2024-shift-2/q087-4.webp",
        "assets/questions/june-2024-shift-2/q087-5.webp",
        "assets/questions/june-2024-shift-2/q087-6.webp",
        "assets/questions/june-2024-shift-2/q087-7.webp"
      ],
      "ocrText": "",
      "correctOptions": [
        3
      ],
      "status": "scored",
      "marks": {
        "correct": 4,
        "incorrect": -1
      },
      "explanation": ""
    },
    {
      "number": 88,
      "questionId": "703088",
      "section": "C",
      "sourcePage": 115,
      "sourceImages": [
        "assets/questions/june-2024-shift-2/q088-1.webp",
        "assets/questions/june-2024-shift-2/q088-2.webp",
        "assets/questions/june-2024-shift-2/q088-3.webp",
        "assets/questions/june-2024-shift-2/q088-4.webp"
      ],
      "ocrText": "",
      "correctOptions": [
        1
      ],
      "status": "scored",
      "marks": {
        "correct": 4,
        "incorrect": -1
      },
      "explanation": ""
    },
    {
      "number": 89,
      "questionId": "703089",
      "section": "C",
      "sourcePage": 118,
      "sourceImages": [
        "assets/questions/june-2024-shift-2/q089-1.webp",
        "assets/questions/june-2024-shift-2/q089-2.webp"
      ],
      "ocrText": "",
      "correctOptions": [
        1
      ],
      "status": "scored",
      "marks": {
        "correct": 4,
        "incorrect": -1
      },
      "explanation": ""
    },
    {
      "number": 90,
      "questionId": "703090",
      "section": "C",
      "sourcePage": 119,
      "sourceImages": [
        "assets/questions/june-2024-shift-2/q090-1.webp",
        "assets/questions/june-2024-shift-2/q090-2.webp",
        "assets/questions/june-2024-shift-2/q090-3.webp",
        "assets/questions/june-2024-shift-2/q090-4.webp"
      ],
      "ocrText": "",
      "correctOptions": [
        3
      ],
      "status": "scored",
      "marks": {
        "correct": 4,
        "incorrect": -1
      },
      "explanation": ""
    },
    {
      "number": 91,
      "questionId": "703091",
      "section": "C",
      "sourcePage": 122,
      "sourceImages": [
        "assets/questions/june-2024-shift-2/q091-1.webp",
        "assets/questions/june-2024-shift-2/q091-2.webp",
        "assets/questions/june-2024-shift-2/q091-3.webp",
        "assets/questions/june-2024-shift-2/q091-4.webp",
        "assets/questions/june-2024-shift-2/q091-5.webp",
        "assets/questions/june-2024-shift-2/q091-6.webp",
        "assets/questions/june-2024-shift-2/q091-7.webp"
      ],
      "ocrText": "",
      "correctOptions": [
        1
      ],
      "status": "scored",
      "marks": {
        "correct": 4,
        "incorrect": -1
      },
      "explanation": ""
    },
    {
      "number": 92,
      "questionId": "703092",
      "section": "C",
      "sourcePage": 128,
      "sourceImages": [
        "assets/questions/june-2024-shift-2/q092-1.webp",
        "assets/questions/june-2024-shift-2/q092-2.webp",
        "assets/questions/june-2024-shift-2/q092-3.webp"
      ],
      "ocrText": "",
      "correctOptions": [
        4
      ],
      "status": "scored",
      "marks": {
        "correct": 4,
        "incorrect": -1
      },
      "explanation": ""
    },
    {
      "number": 93,
      "questionId": "703093",
      "section": "C",
      "sourcePage": 130,
      "sourceImages": [
        "assets/questions/june-2024-shift-2/q093-1.webp",
        "assets/questions/june-2024-shift-2/q093-2.webp",
        "assets/questions/june-2024-shift-2/q093-3.webp"
      ],
      "ocrText": "",
      "correctOptions": [
        2
      ],
      "status": "scored",
      "marks": {
        "correct": 4,
        "incorrect": -1
      },
      "explanation": ""
    },
    {
      "number": 94,
      "questionId": "703094",
      "section": "C",
      "sourcePage": 132,
      "sourceImages": [
        "assets/questions/june-2024-shift-2/q094-1.webp",
        "assets/questions/june-2024-shift-2/q094-2.webp",
        "assets/questions/june-2024-shift-2/q094-3.webp"
      ],
      "ocrText": "",
      "correctOptions": [
        1
      ],
      "status": "scored",
      "marks": {
        "correct": 4,
        "incorrect": -1
      },
      "explanation": ""
    },
    {
      "number": 95,
      "questionId": "703095",
      "section": "C",
      "sourcePage": 134,
      "sourceImages": [
        "assets/questions/june-2024-shift-2/q095-1.webp",
        "assets/questions/june-2024-shift-2/q095-2.webp"
      ],
      "ocrText": "",
      "correctOptions": [
        3
      ],
      "status": "scored",
      "marks": {
        "correct": 4,
        "incorrect": -1
      },
      "explanation": ""
    },
    {
      "number": 96,
      "questionId": "703096",
      "section": "C",
      "sourcePage": 135,
      "sourceImages": [
        "assets/questions/june-2024-shift-2/q096-1.webp",
        "assets/questions/june-2024-shift-2/q096-2.webp",
        "assets/questions/june-2024-shift-2/q096-3.webp"
      ],
      "ocrText": "",
      "correctOptions": [
        2
      ],
      "status": "scored",
      "marks": {
        "correct": 4,
        "incorrect": -1
      },
      "explanation": ""
    },
    {
      "number": 97,
      "questionId": "703097",
      "section": "C",
      "sourcePage": 137,
      "sourceImages": [
        "assets/questions/june-2024-shift-2/q097-1.webp",
        "assets/questions/june-2024-shift-2/q097-2.webp"
      ],
      "ocrText": "",
      "correctOptions": [
        1
      ],
      "status": "scored",
      "marks": {
        "correct": 4,
        "incorrect": -1
      },
      "explanation": ""
    },
    {
      "number": 98,
      "questionId": "703098",
      "section": "C",
      "sourcePage": 138,
      "sourceImages": [
        "assets/questions/june-2024-shift-2/q098-1.webp",
        "assets/questions/june-2024-shift-2/q098-2.webp",
        "assets/questions/june-2024-shift-2/q098-3.webp",
        "assets/questions/june-2024-shift-2/q098-4.webp"
      ],
      "ocrText": "",
      "correctOptions": [
        1
      ],
      "status": "scored",
      "marks": {
        "correct": 4,
        "incorrect": -1
      },
      "explanation": ""
    },
    {
      "number": 99,
      "questionId": "703099",
      "section": "C",
      "sourcePage": 141,
      "sourceImages": [
        "assets/questions/june-2024-shift-2/q099-1.webp",
        "assets/questions/june-2024-shift-2/q099-2.webp"
      ],
      "ocrText": "",
      "correctOptions": [
        4
      ],
      "status": "scored",
      "marks": {
        "correct": 4,
        "incorrect": -1
      },
      "explanation": ""
    },
    {
      "number": 100,
      "questionId": "703100",
      "section": "C",
      "sourcePage": 142,
      "sourceImages": [
        "assets/questions/june-2024-shift-2/q100-1.webp",
        "assets/questions/june-2024-shift-2/q100-2.webp",
        "assets/questions/june-2024-shift-2/q100-3.webp",
        "assets/questions/june-2024-shift-2/q100-4.webp",
        "assets/questions/june-2024-shift-2/q100-5.webp"
      ],
      "ocrText": "",
      "correctOptions": [
        1
      ],
      "status": "scored",
      "marks": {
        "correct": 4,
        "incorrect": -1
      },
      "explanation": ""
    },
    {
      "number": 101,
      "questionId": "703101",
      "section": "C",
      "sourcePage": 146,
      "sourceImages": [
        "assets/questions/june-2024-shift-2/q101-1.webp",
        "assets/questions/june-2024-shift-2/q101-2.webp",
        "assets/questions/june-2024-shift-2/q101-3.webp"
      ],
      "ocrText": "",
      "correctOptions": [
        1
      ],
      "status": "scored",
      "marks": {
        "correct": 4,
        "incorrect": -1
      },
      "explanation": ""
    },
    {
      "number": 102,
      "questionId": "703102",
      "section": "C",
      "sourcePage": 148,
      "sourceImages": [
        "assets/questions/june-2024-shift-2/q102-1.webp",
        "assets/questions/june-2024-shift-2/q102-2.webp",
        "assets/questions/june-2024-shift-2/q102-3.webp",
        "assets/questions/june-2024-shift-2/q102-4.webp",
        "assets/questions/june-2024-shift-2/q102-5.webp",
        "assets/questions/june-2024-shift-2/q102-6.webp",
        "assets/questions/june-2024-shift-2/q102-7.webp"
      ],
      "ocrText": "",
      "correctOptions": [
        3
      ],
      "status": "scored",
      "marks": {
        "correct": 4,
        "incorrect": -1
      },
      "explanation": ""
    },
    {
      "number": 103,
      "questionId": "703103",
      "section": "C",
      "sourcePage": 154,
      "sourceImages": [
        "assets/questions/june-2024-shift-2/q103-1.webp",
        "assets/questions/june-2024-shift-2/q103-2.webp",
        "assets/questions/june-2024-shift-2/q103-3.webp"
      ],
      "ocrText": "",
      "correctOptions": [
        4
      ],
      "status": "scored",
      "marks": {
        "correct": 4,
        "incorrect": -1
      },
      "explanation": ""
    },
    {
      "number": 104,
      "questionId": "703104",
      "section": "C",
      "sourcePage": 156,
      "sourceImages": [
        "assets/questions/june-2024-shift-2/q104-1.webp",
        "assets/questions/june-2024-shift-2/q104-2.webp",
        "assets/questions/june-2024-shift-2/q104-3.webp",
        "assets/questions/june-2024-shift-2/q104-4.webp"
      ],
      "ocrText": "",
      "correctOptions": [
        4
      ],
      "status": "scored",
      "marks": {
        "correct": 4,
        "incorrect": -1
      },
      "explanation": ""
    },
    {
      "number": 105,
      "questionId": "703105",
      "section": "C",
      "sourcePage": 159,
      "sourceImages": [
        "assets/questions/june-2024-shift-2/q105-1.webp",
        "assets/questions/june-2024-shift-2/q105-2.webp"
      ],
      "ocrText": "",
      "correctOptions": [
        4
      ],
      "status": "scored",
      "marks": {
        "correct": 4,
        "incorrect": -1
      },
      "explanation": ""
    },
    {
      "number": 106,
      "questionId": "703106",
      "section": "C",
      "sourcePage": 160,
      "sourceImages": [
        "assets/questions/june-2024-shift-2/q106-1.webp",
        "assets/questions/june-2024-shift-2/q106-2.webp",
        "assets/questions/june-2024-shift-2/q106-3.webp"
      ],
      "ocrText": "",
      "correctOptions": [
        3
      ],
      "status": "scored",
      "marks": {
        "correct": 4,
        "incorrect": -1
      },
      "explanation": ""
    },
    {
      "number": 107,
      "questionId": "703107",
      "section": "C",
      "sourcePage": 162,
      "sourceImages": [
        "assets/questions/june-2024-shift-2/q107-1.webp",
        "assets/questions/june-2024-shift-2/q107-2.webp",
        "assets/questions/june-2024-shift-2/q107-3.webp"
      ],
      "ocrText": "",
      "correctOptions": [
        1
      ],
      "status": "scored",
      "marks": {
        "correct": 4,
        "incorrect": -1
      },
      "explanation": ""
    },
    {
      "number": 108,
      "questionId": "703108",
      "section": "C",
      "sourcePage": 164,
      "sourceImages": [
        "assets/questions/june-2024-shift-2/q108-1.webp",
        "assets/questions/june-2024-shift-2/q108-2.webp"
      ],
      "ocrText": "",
      "correctOptions": [
        4
      ],
      "status": "scored",
      "marks": {
        "correct": 4,
        "incorrect": -1
      },
      "explanation": ""
    },
    {
      "number": 109,
      "questionId": "703109",
      "section": "C",
      "sourcePage": 165,
      "sourceImages": [
        "assets/questions/june-2024-shift-2/q109-1.webp",
        "assets/questions/june-2024-shift-2/q109-2.webp",
        "assets/questions/june-2024-shift-2/q109-3.webp"
      ],
      "ocrText": "",
      "correctOptions": [
        3
      ],
      "status": "scored",
      "marks": {
        "correct": 4,
        "incorrect": -1
      },
      "explanation": ""
    },
    {
      "number": 110,
      "questionId": "703110",
      "section": "C",
      "sourcePage": 167,
      "sourceImages": [
        "assets/questions/june-2024-shift-2/q110-1.webp",
        "assets/questions/june-2024-shift-2/q110-2.webp",
        "assets/questions/june-2024-shift-2/q110-3.webp"
      ],
      "ocrText": "",
      "correctOptions": [
        4
      ],
      "status": "scored",
      "marks": {
        "correct": 4,
        "incorrect": -1
      },
      "explanation": ""
    },
    {
      "number": 111,
      "questionId": "703111",
      "section": "C",
      "sourcePage": 169,
      "sourceImages": [
        "assets/questions/june-2024-shift-2/q111-1.webp",
        "assets/questions/june-2024-shift-2/q111-2.webp",
        "assets/questions/june-2024-shift-2/q111-3.webp"
      ],
      "ocrText": "",
      "correctOptions": [
        1
      ],
      "status": "scored",
      "marks": {
        "correct": 4,
        "incorrect": -1
      },
      "explanation": ""
    },
    {
      "number": 112,
      "questionId": "703112",
      "section": "C",
      "sourcePage": 171,
      "sourceImages": [
        "assets/questions/june-2024-shift-2/q112-1.webp",
        "assets/questions/june-2024-shift-2/q112-2.webp",
        "assets/questions/june-2024-shift-2/q112-3.webp"
      ],
      "ocrText": "",
      "correctOptions": [
        3
      ],
      "status": "scored",
      "marks": {
        "correct": 4,
        "incorrect": -1
      },
      "explanation": ""
    },
    {
      "number": 113,
      "questionId": "703113",
      "section": "C",
      "sourcePage": 173,
      "sourceImages": [
        "assets/questions/june-2024-shift-2/q113-1.webp",
        "assets/questions/june-2024-shift-2/q113-2.webp",
        "assets/questions/june-2024-shift-2/q113-3.webp",
        "assets/questions/june-2024-shift-2/q113-4.webp"
      ],
      "ocrText": "",
      "correctOptions": [
        4
      ],
      "status": "scored",
      "marks": {
        "correct": 4,
        "incorrect": -1
      },
      "explanation": ""
    },
    {
      "number": 114,
      "questionId": "703114",
      "section": "C",
      "sourcePage": 176,
      "sourceImages": [
        "assets/questions/june-2024-shift-2/q114-1.webp",
        "assets/questions/june-2024-shift-2/q114-2.webp",
        "assets/questions/june-2024-shift-2/q114-3.webp"
      ],
      "ocrText": "",
      "correctOptions": [
        2
      ],
      "status": "scored",
      "marks": {
        "correct": 4,
        "incorrect": -1
      },
      "explanation": ""
    },
    {
      "number": 115,
      "questionId": "703115",
      "section": "C",
      "sourcePage": 178,
      "sourceImages": [
        "assets/questions/june-2024-shift-2/q115-1.webp",
        "assets/questions/june-2024-shift-2/q115-2.webp",
        "assets/questions/june-2024-shift-2/q115-3.webp",
        "assets/questions/june-2024-shift-2/q115-4.webp",
        "assets/questions/june-2024-shift-2/q115-5.webp",
        "assets/questions/june-2024-shift-2/q115-6.webp",
        "assets/questions/june-2024-shift-2/q115-7.webp"
      ],
      "ocrText": "",
      "correctOptions": [
        1
      ],
      "status": "scored",
      "marks": {
        "correct": 4,
        "incorrect": -1
      },
      "explanation": ""
    },
    {
      "number": 116,
      "questionId": "703116",
      "section": "C",
      "sourcePage": 184,
      "sourceImages": [
        "assets/questions/june-2024-shift-2/q116-1.webp",
        "assets/questions/june-2024-shift-2/q116-2.webp",
        "assets/questions/june-2024-shift-2/q116-3.webp",
        "assets/questions/june-2024-shift-2/q116-4.webp",
        "assets/questions/june-2024-shift-2/q116-5.webp"
      ],
      "ocrText": "",
      "correctOptions": [
        1
      ],
      "status": "scored",
      "marks": {
        "correct": 4,
        "incorrect": -1
      },
      "explanation": ""
    },
    {
      "number": 117,
      "questionId": "703117",
      "section": "C",
      "sourcePage": 188,
      "sourceImages": [
        "assets/questions/june-2024-shift-2/q117-1.webp",
        "assets/questions/june-2024-shift-2/q117-2.webp",
        "assets/questions/june-2024-shift-2/q117-3.webp",
        "assets/questions/june-2024-shift-2/q117-4.webp",
        "assets/questions/june-2024-shift-2/q117-5.webp"
      ],
      "ocrText": "",
      "correctOptions": [
        2
      ],
      "status": "scored",
      "marks": {
        "correct": 4,
        "incorrect": -1
      },
      "explanation": ""
    },
    {
      "number": 118,
      "questionId": "703118",
      "section": "C",
      "sourcePage": 192,
      "sourceImages": [
        "assets/questions/june-2024-shift-2/q118-1.webp",
        "assets/questions/june-2024-shift-2/q118-2.webp",
        "assets/questions/june-2024-shift-2/q118-3.webp",
        "assets/questions/june-2024-shift-2/q118-4.webp",
        "assets/questions/june-2024-shift-2/q118-5.webp",
        "assets/questions/june-2024-shift-2/q118-6.webp",
        "assets/questions/june-2024-shift-2/q118-7.webp"
      ],
      "ocrText": "",
      "correctOptions": [
        2
      ],
      "status": "scored",
      "marks": {
        "correct": 4,
        "incorrect": -1
      },
      "explanation": ""
    },
    {
      "number": 119,
      "questionId": "703119",
      "section": "C",
      "sourcePage": 198,
      "sourceImages": [
        "assets/questions/june-2024-shift-2/q119-1.webp",
        "assets/questions/june-2024-shift-2/q119-2.webp",
        "assets/questions/june-2024-shift-2/q119-3.webp"
      ],
      "ocrText": "",
      "correctOptions": [
        2
      ],
      "status": "scored",
      "marks": {
        "correct": 4,
        "incorrect": -1
      },
      "explanation": ""
    },
    {
      "number": 120,
      "questionId": "703120",
      "section": "C",
      "sourcePage": 200,
      "sourceImages": [
        "assets/questions/june-2024-shift-2/q120-1.webp",
        "assets/questions/june-2024-shift-2/q120-2.webp",
        "assets/questions/june-2024-shift-2/q120-3.webp"
      ],
      "ocrText": "",
      "correctOptions": [
        3
      ],
      "status": "scored",
      "marks": {
        "correct": 4,
        "incorrect": -1
      },
      "explanation": ""
    },
    {
      "number": 121,
      "questionId": "703121",
      "section": "C",
      "sourcePage": 202,
      "sourceImages": [
        "assets/questions/june-2024-shift-2/q121-1.webp",
        "assets/questions/june-2024-shift-2/q121-2.webp",
        "assets/questions/june-2024-shift-2/q121-3.webp"
      ],
      "ocrText": "",
      "correctOptions": [
        2
      ],
      "status": "scored",
      "marks": {
        "correct": 4,
        "incorrect": -1
      },
      "explanation": ""
    },
    {
      "number": 122,
      "questionId": "703122",
      "section": "C",
      "sourcePage": 204,
      "sourceImages": [
        "assets/questions/june-2024-shift-2/q122-1.webp",
        "assets/questions/june-2024-shift-2/q122-2.webp"
      ],
      "ocrText": "",
      "correctOptions": [
        4
      ],
      "status": "scored",
      "marks": {
        "correct": 4,
        "incorrect": -1
      },
      "explanation": ""
    },
    {
      "number": 123,
      "questionId": "703123",
      "section": "C",
      "sourcePage": 205,
      "sourceImages": [
        "assets/questions/june-2024-shift-2/q123-1.webp",
        "assets/questions/june-2024-shift-2/q123-2.webp"
      ],
      "ocrText": "",
      "correctOptions": [
        1
      ],
      "status": "scored",
      "marks": {
        "correct": 4,
        "incorrect": -1
      },
      "explanation": ""
    },
    {
      "number": 124,
      "questionId": "703124",
      "section": "C",
      "sourcePage": 206,
      "sourceImages": [
        "assets/questions/june-2024-shift-2/q124-1.webp",
        "assets/questions/june-2024-shift-2/q124-2.webp",
        "assets/questions/june-2024-shift-2/q124-3.webp"
      ],
      "ocrText": "",
      "correctOptions": [
        1
      ],
      "status": "scored",
      "marks": {
        "correct": 4,
        "incorrect": -1
      },
      "explanation": ""
    },
    {
      "number": 125,
      "questionId": "703125",
      "section": "C",
      "sourcePage": 208,
      "sourceImages": [
        "assets/questions/june-2024-shift-2/q125-1.webp",
        "assets/questions/june-2024-shift-2/q125-2.webp",
        "assets/questions/june-2024-shift-2/q125-3.webp",
        "assets/questions/june-2024-shift-2/q125-4.webp"
      ],
      "ocrText": "",
      "correctOptions": [
        2
      ],
      "status": "scored",
      "marks": {
        "correct": 4,
        "incorrect": -1
      },
      "explanation": ""
    },
    {
      "number": 126,
      "questionId": "703126",
      "section": "C",
      "sourcePage": 211,
      "sourceImages": [
        "assets/questions/june-2024-shift-2/q126-1.webp",
        "assets/questions/june-2024-shift-2/q126-2.webp"
      ],
      "ocrText": "",
      "correctOptions": [
        1
      ],
      "status": "scored",
      "marks": {
        "correct": 4,
        "incorrect": -1
      },
      "explanation": ""
    },
    {
      "number": 127,
      "questionId": "703127",
      "section": "C",
      "sourcePage": 212,
      "sourceImages": [
        "assets/questions/june-2024-shift-2/q127-1.webp",
        "assets/questions/june-2024-shift-2/q127-2.webp"
      ],
      "ocrText": "",
      "correctOptions": [
        2
      ],
      "status": "scored",
      "marks": {
        "correct": 4,
        "incorrect": -1
      },
      "explanation": ""
    },
    {
      "number": 128,
      "questionId": "703128",
      "section": "C",
      "sourcePage": 213,
      "sourceImages": [
        "assets/questions/june-2024-shift-2/q128-1.webp",
        "assets/questions/june-2024-shift-2/q128-2.webp"
      ],
      "ocrText": "",
      "correctOptions": [
        2
      ],
      "status": "scored",
      "marks": {
        "correct": 4,
        "incorrect": -1
      },
      "explanation": ""
    },
    {
      "number": 129,
      "questionId": "703129",
      "section": "C",
      "sourcePage": 214,
      "sourceImages": [
        "assets/questions/june-2024-shift-2/q129-1.webp",
        "assets/questions/june-2024-shift-2/q129-2.webp",
        "assets/questions/june-2024-shift-2/q129-3.webp"
      ],
      "ocrText": "",
      "correctOptions": [
        2
      ],
      "status": "scored",
      "marks": {
        "correct": 4,
        "incorrect": -1
      },
      "explanation": ""
    },
    {
      "number": 130,
      "questionId": "703130",
      "section": "C",
      "sourcePage": 216,
      "sourceImages": [
        "assets/questions/june-2024-shift-2/q130-1.webp",
        "assets/questions/june-2024-shift-2/q130-2.webp"
      ],
      "ocrText": "",
      "correctOptions": [
        2
      ],
      "status": "scored",
      "marks": {
        "correct": 4,
        "incorrect": -1
      },
      "explanation": ""
    },
    {
      "number": 131,
      "questionId": "703131",
      "section": "C",
      "sourcePage": 217,
      "sourceImages": [
        "assets/questions/june-2024-shift-2/q131-1.webp",
        "assets/questions/june-2024-shift-2/q131-2.webp",
        "assets/questions/june-2024-shift-2/q131-3.webp"
      ],
      "ocrText": "",
      "correctOptions": [
        3
      ],
      "status": "scored",
      "marks": {
        "correct": 4,
        "incorrect": -1
      },
      "explanation": ""
    },
    {
      "number": 132,
      "questionId": "703132",
      "section": "C",
      "sourcePage": 219,
      "sourceImages": [
        "assets/questions/june-2024-shift-2/q132-1.webp",
        "assets/questions/june-2024-shift-2/q132-2.webp",
        "assets/questions/june-2024-shift-2/q132-3.webp"
      ],
      "ocrText": "",
      "correctOptions": [
        3
      ],
      "status": "scored",
      "marks": {
        "correct": 4,
        "incorrect": -1
      },
      "explanation": ""
    },
    {
      "number": 133,
      "questionId": "703133",
      "section": "C",
      "sourcePage": 221,
      "sourceImages": [
        "assets/questions/june-2024-shift-2/q133-1.webp",
        "assets/questions/june-2024-shift-2/q133-2.webp",
        "assets/questions/june-2024-shift-2/q133-3.webp",
        "assets/questions/june-2024-shift-2/q133-4.webp",
        "assets/questions/june-2024-shift-2/q133-5.webp"
      ],
      "ocrText": "",
      "correctOptions": [
        3
      ],
      "status": "scored",
      "marks": {
        "correct": 4,
        "incorrect": -1
      },
      "explanation": ""
    },
    {
      "number": 134,
      "questionId": "703134",
      "section": "C",
      "sourcePage": 225,
      "sourceImages": [
        "assets/questions/june-2024-shift-2/q134-1.webp",
        "assets/questions/june-2024-shift-2/q134-2.webp",
        "assets/questions/june-2024-shift-2/q134-3.webp"
      ],
      "ocrText": "",
      "correctOptions": [
        1
      ],
      "status": "scored",
      "marks": {
        "correct": 4,
        "incorrect": -1
      },
      "explanation": ""
    },
    {
      "number": 135,
      "questionId": "703135",
      "section": "C",
      "sourcePage": 227,
      "sourceImages": [
        "assets/questions/june-2024-shift-2/q135-1.webp",
        "assets/questions/june-2024-shift-2/q135-2.webp"
      ],
      "ocrText": "",
      "correctOptions": [
        4
      ],
      "status": "scored",
      "marks": {
        "correct": 4,
        "incorrect": -1
      },
      "explanation": ""
    },
    {
      "number": 136,
      "questionId": "703136",
      "section": "C",
      "sourcePage": 228,
      "sourceImages": [
        "assets/questions/june-2024-shift-2/q136-1.webp",
        "assets/questions/june-2024-shift-2/q136-2.webp",
        "assets/questions/june-2024-shift-2/q136-3.webp"
      ],
      "ocrText": "",
      "correctOptions": [
        3
      ],
      "status": "scored",
      "marks": {
        "correct": 4,
        "incorrect": -1
      },
      "explanation": ""
    },
    {
      "number": 137,
      "questionId": "703137",
      "section": "C",
      "sourcePage": 230,
      "sourceImages": [
        "assets/questions/june-2024-shift-2/q137-1.webp",
        "assets/questions/june-2024-shift-2/q137-2.webp"
      ],
      "ocrText": "",
      "correctOptions": [
        2
      ],
      "status": "scored",
      "marks": {
        "correct": 4,
        "incorrect": -1
      },
      "explanation": ""
    },
    {
      "number": 138,
      "questionId": "703138",
      "section": "C",
      "sourcePage": 231,
      "sourceImages": [
        "assets/questions/june-2024-shift-2/q138-1.webp",
        "assets/questions/june-2024-shift-2/q138-2.webp",
        "assets/questions/june-2024-shift-2/q138-3.webp",
        "assets/questions/june-2024-shift-2/q138-4.webp"
      ],
      "ocrText": "",
      "correctOptions": [
        4
      ],
      "status": "scored",
      "marks": {
        "correct": 4,
        "incorrect": -1
      },
      "explanation": ""
    },
    {
      "number": 139,
      "questionId": "703139",
      "section": "C",
      "sourcePage": 234,
      "sourceImages": [
        "assets/questions/june-2024-shift-2/q139-1.webp",
        "assets/questions/june-2024-shift-2/q139-2.webp"
      ],
      "ocrText": "",
      "correctOptions": [
        1
      ],
      "status": "scored",
      "marks": {
        "correct": 4,
        "incorrect": -1
      },
      "explanation": ""
    },
    {
      "number": 140,
      "questionId": "703140",
      "section": "C",
      "sourcePage": 235,
      "sourceImages": [
        "assets/questions/june-2024-shift-2/q140-1.webp",
        "assets/questions/june-2024-shift-2/q140-2.webp",
        "assets/questions/june-2024-shift-2/q140-3.webp",
        "assets/questions/june-2024-shift-2/q140-4.webp"
      ],
      "ocrText": "",
      "correctOptions": [
        1
      ],
      "status": "scored",
      "marks": {
        "correct": 4,
        "incorrect": -1
      },
      "explanation": ""
    },
    {
      "number": 141,
      "questionId": "703141",
      "section": "C",
      "sourcePage": 238,
      "sourceImages": [
        "assets/questions/june-2024-shift-2/q141-1.webp",
        "assets/questions/june-2024-shift-2/q141-2.webp",
        "assets/questions/june-2024-shift-2/q141-3.webp",
        "assets/questions/june-2024-shift-2/q141-4.webp"
      ],
      "ocrText": "",
      "correctOptions": [
        2
      ],
      "status": "scored",
      "marks": {
        "correct": 4,
        "incorrect": -1
      },
      "explanation": ""
    },
    {
      "number": 142,
      "questionId": "703142",
      "section": "C",
      "sourcePage": 241,
      "sourceImages": [
        "assets/questions/june-2024-shift-2/q142-1.webp",
        "assets/questions/june-2024-shift-2/q142-2.webp",
        "assets/questions/june-2024-shift-2/q142-3.webp",
        "assets/questions/june-2024-shift-2/q142-4.webp"
      ],
      "ocrText": "",
      "correctOptions": [
        4
      ],
      "status": "scored",
      "marks": {
        "correct": 4,
        "incorrect": -1
      },
      "explanation": ""
    },
    {
      "number": 143,
      "questionId": "703143",
      "section": "C",
      "sourcePage": 244,
      "sourceImages": [
        "assets/questions/june-2024-shift-2/q143-1.webp",
        "assets/questions/june-2024-shift-2/q143-2.webp",
        "assets/questions/june-2024-shift-2/q143-3.webp"
      ],
      "ocrText": "",
      "correctOptions": [
        4
      ],
      "status": "scored",
      "marks": {
        "correct": 4,
        "incorrect": -1
      },
      "explanation": ""
    },
    {
      "number": 144,
      "questionId": "703144",
      "section": "C",
      "sourcePage": 246,
      "sourceImages": [
        "assets/questions/june-2024-shift-2/q144-1.webp",
        "assets/questions/june-2024-shift-2/q144-2.webp",
        "assets/questions/june-2024-shift-2/q144-3.webp",
        "assets/questions/june-2024-shift-2/q144-4.webp"
      ],
      "ocrText": "",
      "correctOptions": [
        3
      ],
      "status": "scored",
      "marks": {
        "correct": 4,
        "incorrect": -1
      },
      "explanation": ""
    },
    {
      "number": 145,
      "questionId": "703145",
      "section": "C",
      "sourcePage": 249,
      "sourceImages": [
        "assets/questions/june-2024-shift-2/q145-1.webp",
        "assets/questions/june-2024-shift-2/q145-2.webp"
      ],
      "ocrText": "",
      "correctOptions": [
        4
      ],
      "status": "scored",
      "marks": {
        "correct": 4,
        "incorrect": -1
      },
      "explanation": ""
    }
  ]
}